meander/__init__.py
meander/contour_compute.py
meander-0.0.3.dist-info/LICENSE
meander-0.0.3.dist-info/METADATA
meander-0.0.3.dist-info/WHEEL
meander-0.0.3.dist-info/top_level.txt
meander-0.0.3.dist-info/RECORD
