Metadata-Version: 2.1
Name: meander
Version: 0.0.3
Summary: Tools for computing contours on 2d surfaces.
Home-page: https://github.com/austinschneider/meander
Author: Austin Schneider
Author-email: austin.schneider@icecube.wisc.edu
License: LGPL-3.0
Platform: UNKNOWN
